dumpwd/__init__.py
dumpwd/__main__.py
dumpwd/__version__.py
dumpwd/_internal/cli.py
dumpwd/_internal/consts.py
dumpwd/api/__init__.py
dumpwd/api/get_contents.py
dumpwd/api/get_inodes.py
dumpwd/api/get_tree.py
dumpwd-0.2.0.dist-info/LICENSE
dumpwd-0.2.0.dist-info/METADATA
dumpwd-0.2.0.dist-info/WHEEL
dumpwd-0.2.0.dist-info/entry_points.txt
dumpwd-0.2.0.dist-info/RECORD
