Metadata-Version: 2.1
Name: dumpwd
Version: 0.2.0
Summary: 
Home-page: https://limboid.ai/dumpwd/
License: MIT
Author: Jacob Valdez
Author-email: jacob.valdez@limboid.ai
Requires-Python: >=3.10,<4.0
Classifier: License :: OSI Approved :: MIT License
Classifier: Programming Language :: Python :: 3
Classifier: Programming Language :: Python :: 3.10
Classifier: Programming Language :: Python :: 3.11
Requires-Dist: typer (>=0.7.0,<0.8.0)
Project-URL: Repository, https://github.com/Limboid/dumpwd
